{
    "authorization": 0,
    "availability": "1",
    "status": true,
    "all_total": 36,
    "total": 36,
    "next_page": null,
    "data": [
        {
            "product_id": "41",
            "title": "Emerald Green",
            "title_ar": "الزمرد الأخضر",
            "product_type": "1",
            "description": "Choose whether you would like your clip plain, printed, with glitter or crystals. Then add your choice of name to the comments and choose whether you would like your clip double sided/with heart.\r\n\r\n\r\n\r\n\r\n\r\n\r\n\r\n\r\n\r\n\r\n\r\n\n",
            "description_ar": "اختر ما إذا كنت تريد أن يكون مقطعك عاديًا أو مطبوعًا أو لامعًا أو بلورات. ثم أضف اختيارك للاسم إلى التعليقات واختر ما إذا كنت تريد مقطعك على الوجهين/مع القلب.\r\n\r\n\r\n\r\n\r\n\r\n\r\n\r\n\r\n\r\n\r\n\r\n\n",
            "sort_order": "0",
            "image": "uploads/product_image/3425/product_01719922631.jpg",
            "current_stock": "45",
            "sale_price": 0,
            "category": "2",
            "sub_category": "0",
            "digital_product": "0",
            "pdt_discount_type": 1,
            "preparation_time": "10080",
            "catering": "0",
            "branches": "ALL",
            "purchase_limit": "0",
            "pdt_tax_id": "0",
            "tag": "",
            "track_inventory": "0",
            "discount": "0.00",
            "special_price_discount": "0",
            "cat_tax_id": "0",
            "preparation_time_text": {
                "en": "7 Days",
                "ar": "7 أيام"
            },
            "description_style": "<p>Choose whether you would like your clip plain, printed, with glitter or crystals. Then add your choice of name to the comments and choose whether you would like your clip double sided/with heart.<br></p>\r\n\r\n\r\n\r\n\r\n\r\n\r\n\r\n\r\n\r\n\r\n\n",
            "description_ar_style": "<p>اختر ما إذا كنت تريد أن يكون مقطعك عاديًا أو مطبوعًا أو لامعًا أو بلورات. ثم أضف اختيارك للاسم إلى التعليقات واختر ما إذا كنت تريد مقطعك على الوجهين/مع القلب.<br></p>\r\n\r\n\r\n\r\n\r\n\r\n\r\n\r\n\r\n\r\n\r\n\n",
            "main_image": "https://ksacdn4.mnasaticdn.com/uploads/product_image/3425/product_01719922631_thumb.jpg",
            "thumb_image": "https://ksacdn4.mnasaticdn.com/uploads/product_image/3425/product_01719922631_thumb.jpg",
            "min_variant_price": 0,
            "original_price": 0,
            "tax_percent": 0,
            "non_taxable": 0,
            "special_tag_en": "",
            "special_tag_ar": "",
            "quantity_discounts": []
        },
        {
            "product_id": "50",
            "title": "Royal Blue",
            "title_ar": "الأزرق الملكي",
            "product_type": "1",
            "description": "Choose whether you would like your clip plain, printed, with glitter or crystals. Then add your choice of name to the comments and choose whether you would like your clip double sided/with heart.\r\n\r\n\r\n\r\n\r\n\r\n\r\n\r\n\r\n\n",
            "description_ar": "اختر ما إذا كنت تريد أن يكون مقطعك عاديًا أو مطبوعًا أو لامعًا أو بلورات. ثم أضف اختيارك للاسم إلى التعليقات واختر ما إذا كنت تريد مقطعك على الوجهين/مع القلب.\r\n\r\n\r\n\r\n\r\n\r\n\r\n\r\n\r\n\n",
            "sort_order": "0",
            "image": "uploads/product_image/3425/product_01719923085.jpg",
            "current_stock": "10",
            "sale_price": 0,
            "category": "2",
            "sub_category": "0",
            "digital_product": "0",
            "pdt_discount_type": 1,
            "preparation_time": "10080",
            "catering": "0",
            "branches": "ALL",
            "purchase_limit": "0",
            "pdt_tax_id": "0",
            "tag": "",
            "track_inventory": "0",
            "discount": "0.00",
            "special_price_discount": "0",
            "cat_tax_id": "0",
            "preparation_time_text": {
                "en": "7 Days",
                "ar": "7 أيام"
            },
            "description_style": "<p>Choose whether you would like your clip plain, printed, with glitter or crystals. Then add your choice of name to the comments and choose whether you would like your clip double sided/with heart.<br></p>\r\n\r\n\r\n\r\n\r\n\r\n\r\n\r\n\n",
            "description_ar_style": "<p>اختر ما إذا كنت تريد أن يكون مقطعك عاديًا أو مطبوعًا أو لامعًا أو بلورات. ثم أضف اختيارك للاسم إلى التعليقات واختر ما إذا كنت تريد مقطعك على الوجهين/مع القلب.<br></p>\r\n\r\n\r\n\r\n\r\n\r\n\r\n\r\n\n",
            "main_image": "https://ksacdn4.mnasaticdn.com/uploads/product_image/3425/product_01719923085_thumb.jpg",
            "thumb_image": "https://ksacdn4.mnasaticdn.com/uploads/product_image/3425/product_01719923085_thumb.jpg",
            "min_variant_price": 0,
            "original_price": 0,
            "tax_percent": 0,
            "non_taxable": 0,
            "special_tag_en": "",
            "special_tag_ar": "",
            "quantity_discounts": []
        },
        {
            "product_id": "53",
            "title": "Summer Nights",
            "title_ar": "ليالي الصيف",
            "product_type": "1",
            "description": "Choose whether you would like your clip plain, printed, with glitter or crystals. Then add your choice of name to the comments and choose whether you would like your clip double sided/with heart.\r\n\r\n\r\n\r\n\r\n\r\n\r\n\r\n\r\n\n",
            "description_ar": "اختر ما إذا كنت تريد أن يكون مقطعك عاديًا أو مطبوعًا أو لامعًا أو بلورات. ثم أضف اختيارك للاسم إلى التعليقات واختر ما إذا كنت تريد مقطعك على الوجهين/مع القلب.\r\n\r\n\r\n\r\n\r\n\r\n\r\n\r\n\r\n\n",
            "sort_order": "0",
            "image": "uploads/product_image/3425/product_01719923146.jpg",
            "current_stock": "0",
            "sale_price": 0,
            "category": "2",
            "sub_category": "0",
            "digital_product": "0",
            "pdt_discount_type": 1,
            "preparation_time": "10080",
            "catering": "0",
            "branches": "ALL",
            "purchase_limit": "0",
            "pdt_tax_id": "0",
            "tag": "",
            "track_inventory": "0",
            "discount": "0.00",
            "special_price_discount": "0",
            "cat_tax_id": "0",
            "preparation_time_text": {
                "en": "7 Days",
                "ar": "7 أيام"
            },
            "description_style": "<p>Choose whether you would like your clip plain, printed, with glitter or crystals. Then add your choice of name to the comments and choose whether you would like your clip double sided/with heart.<br></p>\r\n\r\n\r\n\r\n\r\n\r\n\r\n\r\n\n",
            "description_ar_style": "<p>اختر ما إذا كنت تريد أن يكون مقطعك عاديًا أو مطبوعًا أو لامعًا أو بلورات. ثم أضف اختيارك للاسم إلى التعليقات واختر ما إذا كنت تريد مقطعك على الوجهين/مع القلب.<br></p>\r\n\r\n\r\n\r\n\r\n\r\n\r\n\r\n\n",
            "main_image": "https://ksacdn4.mnasaticdn.com/uploads/product_image/3425/product_01719923146_thumb.jpg",
            "thumb_image": "https://ksacdn4.mnasaticdn.com/uploads/product_image/3425/product_01719923146_thumb.jpg",
            "min_variant_price": 0,
            "original_price": 0,
            "tax_percent": 0,
            "non_taxable": 0,
            "special_tag_en": "",
            "special_tag_ar": "",
            "quantity_discounts": []
        },
        {
            "product_id": "56",
            "title": "Crème Caramel",
            "title_ar": "كريم كراميل",
            "product_type": "1",
            "description": "Choose whether you would like your clip plain, printed, with glitter or crystals. Then add your choice of name to the comments and choose whether you would like your clip double sided/with heart.\r\n\r\n\r\n\r\n\r\n\r\n\r\n\r\n\n",
            "description_ar": "اختر ما إذا كنت تريد أن يكون مقطعك عاديًا أو مطبوعًا أو لامعًا أو بلورات. ثم أضف اختيارك للاسم إلى التعليقات واختر ما إذا كنت تريد مقطعك على الوجهين/مع القلب.\r\n\r\n\r\n\r\n\r\n\r\n\r\n\r\n\n",
            "sort_order": "0",
            "image": "uploads/product_image/3425/product_01719923208.jpg",
            "current_stock": "0",
            "sale_price": 0,
            "category": "2",
            "sub_category": "0",
            "digital_product": "0",
            "pdt_discount_type": 1,
            "preparation_time": "10080",
            "catering": "0",
            "branches": "ALL",
            "purchase_limit": "0",
            "pdt_tax_id": "0",
            "tag": "",
            "track_inventory": "0",
            "discount": "0.00",
            "special_price_discount": "0",
            "cat_tax_id": "0",
            "preparation_time_text": {
                "en": "7 Days",
                "ar": "7 أيام"
            },
            "description_style": "<p>Choose whether you would like your clip plain, printed, with glitter or crystals. Then add your choice of name to the comments and choose whether you would like your clip double sided/with heart.<br></p>\r\n\r\n\r\n\r\n\r\n\r\n\r\n\n",
            "description_ar_style": "<p>اختر ما إذا كنت تريد أن يكون مقطعك عاديًا أو مطبوعًا أو لامعًا أو بلورات. ثم أضف اختيارك للاسم إلى التعليقات واختر ما إذا كنت تريد مقطعك على الوجهين/مع القلب.<br></p>\r\n\r\n\r\n\r\n\r\n\r\n\r\n\n",
            "main_image": "https://ksacdn4.mnasaticdn.com/uploads/product_image/3425/product_01719923208_thumb.jpg",
            "thumb_image": "https://ksacdn4.mnasaticdn.com/uploads/product_image/3425/product_01719923208_thumb.jpg",
            "min_variant_price": 0,
            "original_price": 0,
            "tax_percent": 0,
            "non_taxable": 0,
            "special_tag_en": "",
            "special_tag_ar": "",
            "quantity_discounts": []
        },
        {
            "product_id": "59",
            "title": "Pearly White",
            "title_ar": "أبيض لؤلؤي",
            "product_type": "1",
            "description": "Choose whether you would like your clip plain, printed, with glitter or crystals. Then add your choice of name to the comments and choose whether you would like your clip double sided/with heart.\r\n\r\n\r\n\r\n\r\n\r\n\r\n\n",
            "description_ar": "اختر ما إذا كنت تريد أن يكون مقطعك عاديًا أو مطبوعًا أو لامعًا أو بلورات. ثم أضف اختيارك للاسم إلى التعليقات واختر ما إذا كنت تريد مقطعك على الوجهين/مع القلب.\r\n\r\n\r\n\r\n\r\n\r\n\r\n\n",
            "sort_order": "0",
            "image": "uploads/product_image/3425/product_01719923320.jpg",
            "current_stock": "10",
            "sale_price": 0,
            "category": "2",
            "sub_category": "0",
            "digital_product": "0",
            "pdt_discount_type": 1,
            "preparation_time": "10080",
            "catering": "0",
            "branches": "ALL",
            "purchase_limit": "0",
            "pdt_tax_id": "0",
            "tag": "",
            "track_inventory": "0",
            "discount": "0.00",
            "special_price_discount": "0",
            "cat_tax_id": "0",
            "preparation_time_text": {
                "en": "7 Days",
                "ar": "7 أيام"
            },
            "description_style": "<p>Choose whether you would like your clip plain, printed, with glitter or crystals. Then add your choice of name to the comments and choose whether you would like your clip double sided/with heart.<br></p>\r\n\r\n\r\n\r\n\r\n\r\n\n",
            "description_ar_style": "<p>اختر ما إذا كنت تريد أن يكون مقطعك عاديًا أو مطبوعًا أو لامعًا أو بلورات. ثم أضف اختيارك للاسم إلى التعليقات واختر ما إذا كنت تريد مقطعك على الوجهين/مع القلب.<br></p>\r\n\r\n\r\n\r\n\r\n\r\n\n",
            "main_image": "https://ksacdn4.mnasaticdn.com/uploads/product_image/3425/product_01719923320_thumb.jpg",
            "thumb_image": "https://ksacdn4.mnasaticdn.com/uploads/product_image/3425/product_01719923320_thumb.jpg",
            "min_variant_price": 0,
            "original_price": 0,
            "tax_percent": 0,
            "non_taxable": 0,
            "special_tag_en": "",
            "special_tag_ar": "",
            "quantity_discounts": []
        },
        {
            "product_id": "62",
            "title": "Pink Lollipop",
            "title_ar": "لوليبوب الوردي",
            "product_type": "1",
            "description": "Choose whether you would like your clip plain, printed, with glitter or crystals. Then add your choice of name to the comments and choose whether you would like your clip double sided/with heart.\r\n\r\n\r\n\r\n\r\n\r\n\r\n\n",
            "description_ar": "اختر ما إذا كنت تريد أن يكون مقطعك عاديًا أو مطبوعًا أو لامعًا أو بلورات. ثم أضف اختيارك للاسم إلى التعليقات واختر ما إذا كنت تريد مقطعك على الوجهين/مع القلب.\r\n\r\n\r\n\r\n\r\n\r\n\r\n\n",
            "sort_order": "0",
            "image": "uploads/product_image/3425/product_01719923365.jpg",
            "current_stock": "9",
            "sale_price": 0,
            "category": "2",
            "sub_category": "0",
            "digital_product": "0",
            "pdt_discount_type": 1,
            "preparation_time": "10080",
            "catering": "0",
            "branches": "ALL",
            "purchase_limit": "0",
            "pdt_tax_id": "0",
            "tag": "",
            "track_inventory": "0",
            "discount": "0.00",
            "special_price_discount": "0",
            "cat_tax_id": "0",
            "preparation_time_text": {
                "en": "7 Days",
                "ar": "7 أيام"
            },
            "description_style": "<p>Choose whether you would like your clip plain, printed, with glitter or crystals. Then add your choice of name to the comments and choose whether you would like your clip double sided/with heart.<br></p>\r\n\r\n\r\n\r\n\r\n\r\n\n",
            "description_ar_style": "<p>اختر ما إذا كنت تريد أن يكون مقطعك عاديًا أو مطبوعًا أو لامعًا أو بلورات. ثم أضف اختيارك للاسم إلى التعليقات واختر ما إذا كنت تريد مقطعك على الوجهين/مع القلب.<br></p>\r\n\r\n\r\n\r\n\r\n\r\n\n",
            "main_image": "https://ksacdn4.mnasaticdn.com/uploads/product_image/3425/product_01719923365_thumb.jpg",
            "thumb_image": "https://ksacdn4.mnasaticdn.com/uploads/product_image/3425/product_01719923365_thumb.jpg",
            "min_variant_price": 0,
            "original_price": 0,
            "tax_percent": 0,
            "non_taxable": 0,
            "special_tag_en": "",
            "special_tag_ar": "",
            "quantity_discounts": []
        },
        {
            "product_id": "65",
            "title": "Ocean Blue",
            "title_ar": "اوشن بلو",
            "product_type": "1",
            "description": "Choose whether you would like your clip plain, printed, with glitter or crystals. Then add your choice of name to the comments and choose whether you would like your clip double sided/with heart.\r\n\r\n\r\n\r\n\r\n\r\n\r\n\r\n\r\n\r\n\r\n\r\n\r\n\r\n\r\n\r\n\n",
            "description_ar": "اختر ما إذا كنت تريد أن يكون مقطعك عاديًا أو مطبوعًا أو لامعًا أو بلورات. ثم أضف اختيارك للاسم إلى التعليقات واختر ما إذا كنت تريد مقطعك على الوجهين/مع القلب.\r\n\r\n\r\n\r\n\r\n\r\n\r\n\n",
            "sort_order": "0",
            "image": "uploads/product_image/3425/product_01719923517.jpg",
            "current_stock": "95",
            "sale_price": 0,
            "category": "2",
            "sub_category": "0",
            "digital_product": "0",
            "pdt_discount_type": "1",
            "preparation_time": "10080",
            "catering": "0",
            "branches": "ALL",
            "purchase_limit": "0",
            "pdt_tax_id": "0",
            "tag": "",
            "track_inventory": "0",
            "discount": "10.000",
            "special_price_discount": 0,
            "cat_tax_id": "0",
            "preparation_time_text": {
                "en": "7 Days",
                "ar": "7 أيام"
            },
            "description_style": "<p>Choose whether you would like your clip plain, printed, with glitter or crystals. Then add your choice of name to the comments and choose whether you would like your clip double sided/with heart.<br></p>\r\n\r\n\r\n\r\n\r\n\r\n\r\n\r\n\r\n\r\n\r\n\r\n\r\n\r\n\r\n\n",
            "description_ar_style": "اختر ما إذا كنت تريد أن يكون مقطعك عاديًا أو مطبوعًا أو لامعًا أو بلورات. ثم أضف اختيارك للاسم إلى التعليقات واختر ما إذا كنت تريد مقطعك على الوجهين/مع القلب.\r\n\r\n\r\n\r\n\r\n\r\n\r\n\n",
            "main_image": "https://ksacdn4.mnasaticdn.com/uploads/product_image/3425/product_01719923517_thumb.jpg",
            "thumb_image": "https://ksacdn4.mnasaticdn.com/uploads/product_image/3425/product_01719923517_thumb.jpg",
            "min_variant_price": 0,
            "original_price": 0,
            "tax_percent": 0,
            "non_taxable": 0,
            "special_tag_en": "",
            "special_tag_ar": "",
            "quantity_discounts": []
        },
        {
            "product_id": "68",
            "title": "Sunset Pink",
            "title_ar": "سانست بينك",
            "product_type": "1",
            "description": "Choose whether you would like your clip plain, printed, with glitter or crystals. Then add your choice of name to the comments and choose whether you would like your clip double sided/with heart.\r\n\r\n\r\n\r\n\r\n\r\n\r\n\r\n\n",
            "description_ar": "اختر ما إذا كنت تريد أن يكون مقطعك عاديًا أو مطبوعًا أو لامعًا أو بلورات. ثم أضف اختيارك للاسم إلى التعليقات واختر ما إذا كنت تريد مقطعك على الوجهين/مع القلب.\r\n\r\n\r\n\r\n\r\n\r\n\r\n\r\n\n",
            "sort_order": "0",
            "image": "uploads/product_image/3425/product_01719923591.jpg",
            "current_stock": "11",
            "sale_price": 0,
            "category": "2",
            "sub_category": "0",
            "digital_product": "0",
            "pdt_discount_type": 1,
            "preparation_time": "10080",
            "catering": "0",
            "branches": "ALL",
            "purchase_limit": "0",
            "pdt_tax_id": "0",
            "tag": "",
            "track_inventory": "0",
            "discount": "0.00",
            "special_price_discount": "0",
            "cat_tax_id": "0",
            "preparation_time_text": {
                "en": "7 Days",
                "ar": "7 أيام"
            },
            "description_style": "<p>Choose whether you would like your clip plain, printed, with glitter or crystals. Then add your choice of name to the comments and choose whether you would like your clip double sided/with heart.<br></p>\r\n\r\n\r\n\r\n\r\n\r\n\r\n\n",
            "description_ar_style": "<p>اختر ما إذا كنت تريد أن يكون مقطعك عاديًا أو مطبوعًا أو لامعًا أو بلورات. ثم أضف اختيارك للاسم إلى التعليقات واختر ما إذا كنت تريد مقطعك على الوجهين/مع القلب.<br></p>\r\n\r\n\r\n\r\n\r\n\r\n\r\n\n",
            "main_image": "https://ksacdn4.mnasaticdn.com/uploads/product_image/3425/product_01719923591_thumb.jpg",
            "thumb_image": "https://ksacdn4.mnasaticdn.com/uploads/product_image/3425/product_01719923591_thumb.jpg",
            "min_variant_price": 0,
            "original_price": 0,
            "tax_percent": 0,
            "non_taxable": 0,
            "special_tag_en": "",
            "special_tag_ar": "",
            "quantity_discounts": []
        },
        {
            "product_id": "71",
            "title": "Lights Off",
            "title_ar": "لايتس اوف",
            "product_type": "1",
            "description": "Choose whether you would like your clip plain, printed, with glitter or crystals. Then add your choice of name to the comments and choose whether you would like your clip double sided/with heart.\r\n\r\n\r\n\r\n\r\n\r\n\r\n\r\n\n",
            "description_ar": "اختر ما إذا كنت تريد أن يكون مقطعك عاديًا أو مطبوعًا أو لامعًا أو بلورات. ثم أضف اختيارك للاسم إلى التعليقات واختر ما إذا كنت تريد مقطعك على الوجهين/مع القلب.\r\n\r\n\r\n\r\n\r\n\r\n\r\n\r\n\n",
            "sort_order": "0",
            "image": "uploads/product_image/3425/product_01719923642.jpg",
            "current_stock": "18",
            "sale_price": 0,
            "category": "2",
            "sub_category": "0",
            "digital_product": "0",
            "pdt_discount_type": 1,
            "preparation_time": "10080",
            "catering": "0",
            "branches": "ALL",
            "purchase_limit": "0",
            "pdt_tax_id": "0",
            "tag": "",
            "track_inventory": "0",
            "discount": "0.00",
            "special_price_discount": "0",
            "cat_tax_id": "0",
            "preparation_time_text": {
                "en": "7 Days",
                "ar": "7 أيام"
            },
            "description_style": "<p>Choose whether you would like your clip plain, printed, with glitter or crystals. Then add your choice of name to the comments and choose whether you would like your clip double sided/with heart.<br></p>\r\n\r\n\r\n\r\n\r\n\r\n\r\n\n",
            "description_ar_style": "<p>اختر ما إذا كنت تريد أن يكون مقطعك عاديًا أو مطبوعًا أو لامعًا أو بلورات. ثم أضف اختيارك للاسم إلى التعليقات واختر ما إذا كنت تريد مقطعك على الوجهين/مع القلب.<br></p>\r\n\r\n\r\n\r\n\r\n\r\n\r\n\n",
            "main_image": "https://ksacdn4.mnasaticdn.com/uploads/product_image/3425/product_01719923642_thumb.jpg",
            "thumb_image": "https://ksacdn4.mnasaticdn.com/uploads/product_image/3425/product_01719923642_thumb.jpg",
            "min_variant_price": 0,
            "original_price": 0,
            "tax_percent": 0,
            "non_taxable": 0,
            "special_tag_en": "",
            "special_tag_ar": "",
            "quantity_discounts": []
        },
        {
            "product_id": "74",
            "title": "Snow White",
            "title_ar": "سنو وايت",
            "product_type": "1",
            "description": "Choose whether you would like your clip plain, printed, with glitter or crystals. Then add your choice of name to the comments and choose whether you would like your clip double sided/with heart.\r\n\r\n\r\n\r\n\r\n\r\n\r\n\r\n\r\n\n",
            "description_ar": "اختر ما إذا كنت تريد أن يكون مقطعك عاديًا أو مطبوعًا أو لامعًا أو بلورات. ثم أضف اختيارك للاسم إلى التعليقات واختر ما إذا كنت تريد مقطعك على الوجهين/مع القلب.\r\n\r\n\r\n\r\n\r\n\r\n\r\n\r\n\r\n\n",
            "sort_order": "0",
            "image": "uploads/product_image/3425/product_01719923706.jpg",
            "current_stock": "9",
            "sale_price": 1,
            "category": "2",
            "sub_category": "0",
            "digital_product": "0",
            "pdt_discount_type": 1,
            "preparation_time": "10080",
            "catering": "0",
            "branches": "ALL",
            "purchase_limit": "0",
            "pdt_tax_id": "0",
            "tag": "",
            "track_inventory": "0",
            "discount": "0.00",
            "special_price_discount": "0",
            "cat_tax_id": "0",
            "preparation_time_text": {
                "en": "7 Days",
                "ar": "7 أيام"
            },
            "description_style": "<p>Choose whether you would like your clip plain, printed, with glitter or crystals. Then add your choice of name to the comments and choose whether you would like your clip double sided/with heart.<br></p>\r\n\r\n\r\n\r\n\r\n\r\n\r\n\r\n\n",
            "description_ar_style": "<p>اختر ما إذا كنت تريد أن يكون مقطعك عاديًا أو مطبوعًا أو لامعًا أو بلورات. ثم أضف اختيارك للاسم إلى التعليقات واختر ما إذا كنت تريد مقطعك على الوجهين/مع القلب.<br></p>\r\n\r\n\r\n\r\n\r\n\r\n\r\n\r\n\n",
            "main_image": "https://ksacdn4.mnasaticdn.com/uploads/product_image/3425/product_01719923706_thumb.jpg",
            "thumb_image": "https://ksacdn4.mnasaticdn.com/uploads/product_image/3425/product_01719923706_thumb.jpg",
            "min_variant_price": 0,
            "original_price": 1,
            "tax_percent": 0,
            "non_taxable": 0,
            "special_tag_en": "",
            "special_tag_ar": "",
            "quantity_discounts": []
        },
        {
            "product_id": "77",
            "title": "True White",
            "title_ar": "ترو وايت",
            "product_type": "1",
            "description": "Choose whether you would like your clip plain, printed, with glitter or crystals. Then add your choice of name to the comments and choose whether you would like your clip double sided/with heart.\r\n\r\n\r\n\r\n\r\n\r\n\r\n\r\n\r\n\n",
            "description_ar": "اختر ما إذا كنت تريد أن يكون مقطعك عاديًا أو مطبوعًا أو لامعًا أو بلورات. ثم أضف اختيارك للاسم إلى التعليقات واختر ما إذا كنت تريد مقطعك على الوجهين/مع القلب.\r\n\r\n\r\n\r\n\r\n\r\n\r\n\r\n\r\n\n",
            "sort_order": "0",
            "image": "uploads/product_image/3425/product_01719923776.jpg",
            "current_stock": "8",
            "sale_price": 0,
            "category": "2",
            "sub_category": "0",
            "digital_product": "0",
            "pdt_discount_type": 1,
            "preparation_time": "10080",
            "catering": "0",
            "branches": "ALL",
            "purchase_limit": "0",
            "pdt_tax_id": "0",
            "tag": "",
            "track_inventory": "0",
            "discount": "0.00",
            "special_price_discount": "0",
            "cat_tax_id": "0",
            "preparation_time_text": {
                "en": "7 Days",
                "ar": "7 أيام"
            },
            "description_style": "<p>Choose whether you would like your clip plain, printed, with glitter or crystals. Then add your choice of name to the comments and choose whether you would like your clip double sided/with heart.<br></p>\r\n\r\n\r\n\r\n\r\n\r\n\r\n\r\n\n",
            "description_ar_style": "<p>اختر ما إذا كنت تريد أن يكون مقطعك عاديًا أو مطبوعًا أو لامعًا أو بلورات. ثم أضف اختيارك للاسم إلى التعليقات واختر ما إذا كنت تريد مقطعك على الوجهين/مع القلب.<br></p>\r\n\r\n\r\n\r\n\r\n\r\n\r\n\r\n\n",
            "main_image": "https://ksacdn4.mnasaticdn.com/uploads/product_image/3425/product_01719923776_thumb.jpg",
            "thumb_image": "https://ksacdn4.mnasaticdn.com/uploads/product_image/3425/product_01719923776_thumb.jpg",
            "min_variant_price": 0,
            "original_price": 0,
            "tax_percent": 0,
            "non_taxable": 0,
            "special_tag_en": "",
            "special_tag_ar": "",
            "quantity_discounts": []
        },
        {
            "product_id": "80",
            "title": "Amethyst Haze",
            "title_ar": "امثيست هايذ",
            "product_type": "1",
            "description": "Choose whether you would like your clip plain, printed, with glitter or crystals. Then add your choice of name to the comments and choose whether you would like your clip double sided/with heart.\r\n\r\n\r\n\r\n\r\n\r\n\r\n\n",
            "description_ar": "اختر ما إذا كنت تريد أن يكون مقطعك عاديًا أو مطبوعًا أو لامعًا أو بلورات. ثم أضف اختيارك للاسم إلى التعليقات واختر ما إذا كنت تريد مقطعك على الوجهين/مع القلب.\r\n\r\n\r\n\r\n\r\n\r\n\r\n\n",
            "sort_order": "0",
            "image": "uploads/product_image/3425/product_01719923825.jpg",
            "current_stock": "17",
            "sale_price": 0,
            "category": "2",
            "sub_category": "0",
            "digital_product": "0",
            "pdt_discount_type": 1,
            "preparation_time": "10080",
            "catering": "0",
            "branches": "ALL",
            "purchase_limit": "0",
            "pdt_tax_id": "0",
            "tag": "",
            "track_inventory": "0",
            "discount": "0.00",
            "special_price_discount": "0",
            "cat_tax_id": "0",
            "preparation_time_text": {
                "en": "7 Days",
                "ar": "7 أيام"
            },
            "description_style": "<p>Choose whether you would like your clip plain, printed, with glitter or crystals. Then add your choice of name to the comments and choose whether you would like your clip double sided/with heart.<br></p>\r\n\r\n\r\n\r\n\r\n\r\n\n",
            "description_ar_style": "<p>اختر ما إذا كنت تريد أن يكون مقطعك عاديًا أو مطبوعًا أو لامعًا أو بلورات. ثم أضف اختيارك للاسم إلى التعليقات واختر ما إذا كنت تريد مقطعك على الوجهين/مع القلب.<br></p>\r\n\r\n\r\n\r\n\r\n\r\n\n",
            "main_image": "https://ksacdn4.mnasaticdn.com/uploads/product_image/3425/product_01719923825_thumb.jpg",
            "thumb_image": "https://ksacdn4.mnasaticdn.com/uploads/product_image/3425/product_01719923825_thumb.jpg",
            "min_variant_price": 0,
            "original_price": 0,
            "tax_percent": 0,
            "non_taxable": 0,
            "special_tag_en": "",
            "special_tag_ar": "",
            "quantity_discounts": []
        },
        {
            "product_id": "86",
            "title": "Ballerina Pink",
            "title_ar": "بالرينا الوردية",
            "product_type": "1",
            "description": "Choose whether you would like your clip plain, printed, with glitter or crystals. Then add your choice of name to the comments and choose whether you would like your clip double sided/with heart.\r\n\r\n\r\n\r\n\r\n\r\n\r\n\r\n\r\n\r\n\n",
            "description_ar": "اختر ما إذا كنت تريد أن يكون مقطعك عاديًا أو مطبوعًا أو لامعًا أو بلورات. ثم أضف اختيارك للاسم إلى التعليقات واختر ما إذا كنت تريد مقطعك على الوجهين/مع القلب.\r\n\r\n\r\n\r\n\r\n\r\n\r\n\r\n\r\n\r\n\n",
            "sort_order": "0",
            "image": "uploads/product_image/3425/product_01720593380.jpg",
            "current_stock": "30",
            "sale_price": 0,
            "category": "2",
            "sub_category": "0",
            "digital_product": "0",
            "pdt_discount_type": 1,
            "preparation_time": "10080",
            "catering": "0",
            "branches": "ALL",
            "purchase_limit": "0",
            "pdt_tax_id": "0",
            "tag": "",
            "track_inventory": "0",
            "discount": "0.00",
            "special_price_discount": "0",
            "cat_tax_id": "0",
            "preparation_time_text": {
                "en": "7 Days",
                "ar": "7 أيام"
            },
            "description_style": "<p>Choose whether you would like your clip plain, printed, with glitter or crystals. Then add your choice of name to the comments and choose whether you would like your clip double sided/with heart.<br></p>\r\n\r\n\r\n\r\n\r\n\r\n\r\n\r\n\r\n\n",
            "description_ar_style": "<p>اختر ما إذا كنت تريد أن يكون مقطعك عاديًا أو مطبوعًا أو لامعًا أو بلورات. ثم أضف اختيارك للاسم إلى التعليقات واختر ما إذا كنت تريد مقطعك على الوجهين/مع القلب.<br></p>\r\n\r\n\r\n\r\n\r\n\r\n\r\n\r\n\r\n\n",
            "main_image": "https://ksacdn4.mnasaticdn.com/uploads/product_image/3425/product_01720593380_thumb.jpg",
            "thumb_image": "https://ksacdn4.mnasaticdn.com/uploads/product_image/3425/product_01720593380_thumb.jpg",
            "min_variant_price": 0,
            "original_price": 0,
            "tax_percent": 0,
            "non_taxable": 0,
            "special_tag_en": "",
            "special_tag_ar": "",
            "quantity_discounts": []
        },
        {
            "product_id": "88",
            "title": "Spring Day",
            "title_ar": "يوم الربيع",
            "product_type": "1",
            "description": "Choose whether you would like your clip plain, printed, with glitter or crystals. Then add your choice of name to the comments and choose whether you would like your clip double sided/with heart.\r\n\r\n\r\n\r\n\r\n\r\n\n",
            "description_ar": "اختر ما إذا كنت تريد أن يكون مقطعك عاديًا أو مطبوعًا أو لامعًا أو بلورات. ثم أضف اختيارك للاسم إلى التعليقات واختر ما إذا كنت تريد مقطعك على الوجهين/مع القلب.\r\n\n",
            "sort_order": "0",
            "image": "uploads/product_image/3425/product_01720593506.jpg",
            "current_stock": "9",
            "sale_price": 0,
            "category": "2",
            "sub_category": "0",
            "digital_product": "0",
            "pdt_discount_type": 1,
            "preparation_time": "10080",
            "catering": "0",
            "branches": "ALL",
            "purchase_limit": "0",
            "pdt_tax_id": "0",
            "tag": "",
            "track_inventory": "0",
            "discount": "0.00",
            "special_price_discount": "0",
            "cat_tax_id": "0",
            "preparation_time_text": {
                "en": "7 Days",
                "ar": "7 أيام"
            },
            "description_style": "<p>Choose whether you would like your clip plain, printed, with glitter or crystals. Then add your choice of name to the comments and choose whether you would like your clip double sided/with heart.<br></p>\r\n\r\n\r\n\r\n\r\n\n",
            "description_ar_style": "اختر ما إذا كنت تريد أن يكون مقطعك عاديًا أو مطبوعًا أو لامعًا أو بلورات. ثم أضف اختيارك للاسم إلى التعليقات واختر ما إذا كنت تريد مقطعك على الوجهين/مع القلب.\r\n\n",
            "main_image": "https://ksacdn4.mnasaticdn.com/uploads/product_image/3425/product_01720593506_thumb.jpg",
            "thumb_image": "https://ksacdn4.mnasaticdn.com/uploads/product_image/3425/product_01720593506_thumb.jpg",
            "min_variant_price": 0,
            "original_price": 0,
            "tax_percent": 0,
            "non_taxable": 0,
            "special_tag_en": "",
            "special_tag_ar": "",
            "quantity_discounts": []
        },
        {
            "product_id": "122",
            "title": "Santorini Blue",
            "title_ar": "Santorini Blue",
            "product_type": "1",
            "description": "Collection 03\n",
            "description_ar": "Collection 03\r\n\n",
            "sort_order": "0",
            "image": "uploads/product_image/3425/product_01725732943.jpg",
            "current_stock": "10",
            "sale_price": 1,
            "category": "2",
            "sub_category": "0",
            "digital_product": "0",
            "pdt_discount_type": 1,
            "preparation_time": "2880",
            "catering": "0",
            "branches": "ALL",
            "purchase_limit": "0",
            "pdt_tax_id": "0",
            "tag": "__tag_new",
            "track_inventory": "0",
            "discount": "0.00",
            "special_price_discount": "0",
            "cat_tax_id": "0",
            "preparation_time_text": {
                "en": "2 Days",
                "ar": "2 يوم"
            },
            "description_style": "Collection 03\n",
            "description_ar_style": "<p>Collection 03<br></p>\n",
            "main_image": "https://ksacdn4.mnasaticdn.com/uploads/product_image/3425/product_01725732943_thumb.jpg",
            "thumb_image": "https://ksacdn4.mnasaticdn.com/uploads/product_image/3425/product_01725732943_thumb.jpg",
            "min_variant_price": 0,
            "original_price": 1,
            "tax_percent": 0,
            "non_taxable": 0,
            "special_tag_en": "New",
            "special_tag_ar": "جديد",
            "quantity_discounts": []
        },
        {
            "product_id": "125",
            "title": "Sugar Glaze",
            "title_ar": "Sugar Glaze",
            "product_type": "1",
            "description": "Collection 03\r\n\n",
            "description_ar": "Collection 03\r\n\r\n\n",
            "sort_order": "0",
            "image": "uploads/product_image/3425/product_01725733033.jpg",
            "current_stock": "6",
            "sale_price": 1,
            "category": "2",
            "sub_category": "0",
            "digital_product": "0",
            "pdt_discount_type": 1,
            "preparation_time": "4320",
            "catering": "0",
            "branches": "ALL",
            "purchase_limit": "0",
            "pdt_tax_id": "0",
            "tag": "__tag_new",
            "track_inventory": "0",
            "discount": "0.00",
            "special_price_discount": "0",
            "cat_tax_id": "0",
            "preparation_time_text": {
                "en": "3 Days",
                "ar": "3 أيام"
            },
            "description_style": "<p>Collection 03</p>\r\n\n",
            "description_ar_style": "<p>Collection 03<br></p>\r\n\n",
            "main_image": "https://ksacdn4.mnasaticdn.com/uploads/product_image/3425/product_01725733033_thumb.jpg",
            "thumb_image": "https://ksacdn4.mnasaticdn.com/uploads/product_image/3425/product_01725733033_thumb.jpg",
            "min_variant_price": 0,
            "original_price": 1,
            "tax_percent": 0,
            "non_taxable": 0,
            "special_tag_en": "New",
            "special_tag_ar": "جديد",
            "quantity_discounts": []
        },
        {
            "product_id": "128",
            "title": "Cotton Candy",
            "title_ar": "Cotton Candy",
            "product_type": "1",
            "description": "Collection 03\n",
            "description_ar": "Collection 03\n",
            "sort_order": "0",
            "image": "uploads/product_image/3425/product_01725733149.jpg",
            "current_stock": "6",
            "sale_price": 1,
            "category": "2",
            "sub_category": "0",
            "digital_product": "0",
            "pdt_discount_type": 1,
            "preparation_time": "0",
            "catering": "0",
            "branches": "ALL",
            "purchase_limit": "0",
            "pdt_tax_id": "0",
            "tag": "__tag_new",
            "track_inventory": "0",
            "discount": "0.00",
            "special_price_discount": "0",
            "cat_tax_id": "0",
            "description_style": "<p>Collection 03</p>\n",
            "description_ar_style": "<p>Collection 03</p>\n",
            "main_image": "https://ksacdn4.mnasaticdn.com/uploads/product_image/3425/product_01725733149_thumb.jpg",
            "thumb_image": "https://ksacdn4.mnasaticdn.com/uploads/product_image/3425/product_01725733149_thumb.jpg",
            "min_variant_price": 0,
            "original_price": 1,
            "tax_percent": 0,
            "non_taxable": 0,
            "special_tag_en": "New",
            "special_tag_ar": "جديد",
            "quantity_discounts": []
        },
        {
            "product_id": "131",
            "title": "Buttercream",
            "title_ar": "Buttercream",
            "product_type": "1",
            "description": "Collection 03\r\n\n",
            "description_ar": "Collection 03\r\n\r\n\n",
            "sort_order": "0",
            "image": "uploads/product_image/3425/product_01725733249.jpg",
            "current_stock": "2",
            "sale_price": 1,
            "category": "2",
            "sub_category": "0",
            "digital_product": "0",
            "pdt_discount_type": 1,
            "preparation_time": "4320",
            "catering": "0",
            "branches": "ALL",
            "purchase_limit": "0",
            "pdt_tax_id": "0",
            "tag": "__tag_new",
            "track_inventory": "0",
            "discount": "0.00",
            "special_price_discount": "0",
            "cat_tax_id": "0",
            "preparation_time_text": {
                "en": "3 Days",
                "ar": "3 أيام"
            },
            "description_style": "<p>Collection 03</p>\r\n\n",
            "description_ar_style": "<p>Collection 03<br></p>\r\n\n",
            "main_image": "https://ksacdn4.mnasaticdn.com/uploads/product_image/3425/product_01725733249_thumb.jpg",
            "thumb_image": "https://ksacdn4.mnasaticdn.com/uploads/product_image/3425/product_01725733249_thumb.jpg",
            "min_variant_price": 0,
            "original_price": 1,
            "tax_percent": 0,
            "non_taxable": 0,
            "special_tag_en": "New",
            "special_tag_ar": "جديد",
            "quantity_discounts": []
        },
        {
            "product_id": "134",
            "title": "Vanilla Biscuit",
            "title_ar": "Vanilla Biscuit",
            "product_type": "1",
            "description": "Collection 03\n",
            "description_ar": "Collection 03\r\n\n",
            "sort_order": "0",
            "image": "uploads/product_image/3425/product_01725733345.jpg",
            "current_stock": "15",
            "sale_price": 1,
            "category": "2",
            "sub_category": "0",
            "digital_product": "0",
            "pdt_discount_type": 1,
            "preparation_time": "4320",
            "catering": "0",
            "branches": "ALL",
            "purchase_limit": "0",
            "pdt_tax_id": "0",
            "tag": "__tag_new",
            "track_inventory": "0",
            "discount": "0.00",
            "special_price_discount": "0",
            "cat_tax_id": "0",
            "preparation_time_text": {
                "en": "3 Days",
                "ar": "3 أيام"
            },
            "description_style": "<p>Collection 03</p>\n",
            "description_ar_style": "<p>Collection 03<br></p>\n",
            "main_image": "https://ksacdn4.mnasaticdn.com/uploads/product_image/3425/product_01725733345_thumb.jpg",
            "thumb_image": "https://ksacdn4.mnasaticdn.com/uploads/product_image/3425/product_01725733345_thumb.jpg",
            "min_variant_price": 0,
            "original_price": 1,
            "tax_percent": 0,
            "non_taxable": 0,
            "special_tag_en": "New",
            "special_tag_ar": "جديد",
            "quantity_discounts": []
        },
        {
            "product_id": "137",
            "title": "Garden Fairy",
            "title_ar": "Garden Fairy",
            "product_type": "1",
            "description": "Choose whether you would like your clip plain, printed, with glitter or crystals. Then add your choice of name to the comments and choose whether you would like your clip double sided/with heart.\r\n\r\n\n",
            "description_ar": "اختر ما إذا كنت تريد أن يكون مقطعك عاديًا أو مطبوعًا أو لامعًا أو بلورات. ثم أضف اختيارك للاسم إلى التعليقات واختر ما إذا كنت تريد مقطعك على الوجهين/مع القلب.\r\n\r\n\n",
            "sort_order": "0",
            "image": "uploads/product_image/3425/product_01725733628.jpg",
            "current_stock": "16",
            "sale_price": 1,
            "category": "2",
            "sub_category": "0",
            "digital_product": "0",
            "pdt_discount_type": 1,
            "preparation_time": "4320",
            "catering": "0",
            "branches": "ALL",
            "purchase_limit": "0",
            "pdt_tax_id": "0",
            "tag": "__tag_new",
            "track_inventory": "0",
            "discount": "0.00",
            "special_price_discount": "0",
            "cat_tax_id": "0",
            "preparation_time_text": {
                "en": "3 Days",
                "ar": "3 أيام"
            },
            "description_style": "<p>Choose whether you would like your clip plain, printed, with glitter or crystals. Then add your choice of name to the comments and choose whether you would like your clip double sided/with heart.<br></p>\r\n\n",
            "description_ar_style": "<p>اختر ما إذا كنت تريد أن يكون مقطعك عاديًا أو مطبوعًا أو لامعًا أو بلورات. ثم أضف اختيارك للاسم إلى التعليقات واختر ما إذا كنت تريد مقطعك على الوجهين/مع القلب.<br></p>\r\n\n",
            "main_image": "https://ksacdn4.mnasaticdn.com/uploads/product_image/3425/product_01725733628_thumb.jpg",
            "thumb_image": "https://ksacdn4.mnasaticdn.com/uploads/product_image/3425/product_01725733628_thumb.jpg",
            "min_variant_price": 0,
            "original_price": 1,
            "tax_percent": 0,
            "non_taxable": 0,
            "special_tag_en": "New",
            "special_tag_ar": "جديد",
            "quantity_discounts": []
        },
        {
            "product_id": "140",
            "title": "Leopard",
            "title_ar": "Leopard",
            "product_type": "1",
            "description": "Choose whether you would like your clip plain, printed, with glitter or crystals. Then add your choice of name to the comments and choose whether you would like your clip double sided/with heart.\r\n\r\n\n",
            "description_ar": "اختر ما إذا كنت تريد أن يكون مقطعك عاديًا أو مطبوعًا أو لامعًا أو بلورات. ثم أضف اختيارك للاسم إلى التعليقات واختر ما إذا كنت تريد مقطعك على الوجهين/مع القلب.\r\n\r\n\n",
            "sort_order": "0",
            "image": "uploads/product_image/3425/product_01725733746.jpg",
            "current_stock": "135",
            "sale_price": 1,
            "category": "2",
            "sub_category": "0",
            "digital_product": "0",
            "pdt_discount_type": 1,
            "preparation_time": "4320",
            "catering": "0",
            "branches": "ALL",
            "purchase_limit": "0",
            "pdt_tax_id": "0",
            "tag": "",
            "track_inventory": "0",
            "discount": "0.00",
            "special_price_discount": "0",
            "cat_tax_id": "0",
            "preparation_time_text": {
                "en": "3 Days",
                "ar": "3 أيام"
            },
            "description_style": "<p>Choose whether you would like your clip plain, printed, with glitter or crystals. Then add your choice of name to the comments and choose whether you would like your clip double sided/with heart.<br></p>\r\n\n",
            "description_ar_style": "<p>اختر ما إذا كنت تريد أن يكون مقطعك عاديًا أو مطبوعًا أو لامعًا أو بلورات. ثم أضف اختيارك للاسم إلى التعليقات واختر ما إذا كنت تريد مقطعك على الوجهين/مع القلب.<br></p>\r\n\n",
            "main_image": "https://ksacdn4.mnasaticdn.com/uploads/product_image/3425/product_01725733746_thumb.jpg",
            "thumb_image": "https://ksacdn4.mnasaticdn.com/uploads/product_image/3425/product_01725733746_thumb.jpg",
            "min_variant_price": 0,
            "original_price": 1,
            "tax_percent": 0,
            "non_taxable": 0,
            "special_tag_en": "",
            "special_tag_ar": "",
            "quantity_discounts": []
        },
        {
            "product_id": "143",
            "title": "Titanic",
            "title_ar": "Titanic",
            "product_type": "1",
            "description": "Choose whether you would like your clip plain, printed, with glitter or crystals. Then add your choice of name to the comments and choose whether you would like your clip double sided/with heart.\r\n\n",
            "description_ar": "اختر ما إذا كنت تريد أن يكون مقطعك عاديًا أو مطبوعًا أو لامعًا أو بلورات. ثم أضف اختيارك للاسم إلى التعليقات واختر ما إذا كنت تريد مقطعك على الوجهين/مع القلب.\r\n\n",
            "sort_order": "0",
            "image": "uploads/product_image/3425/product_01725733862.jpg",
            "current_stock": "11",
            "sale_price": 1,
            "category": "2",
            "sub_category": "0",
            "digital_product": "0",
            "pdt_discount_type": 1,
            "preparation_time": "4320",
            "catering": "0",
            "branches": "ALL",
            "purchase_limit": "0",
            "pdt_tax_id": "0",
            "tag": "__tag_new",
            "track_inventory": "0",
            "discount": "0.00",
            "special_price_discount": "0",
            "cat_tax_id": "0",
            "preparation_time_text": {
                "en": "3 Days",
                "ar": "3 أيام"
            },
            "description_style": "<p>Choose whether you would like your clip plain, printed, with glitter or crystals. Then add your choice of name to the comments and choose whether you would like your clip double sided/with heart.<br></p>\n",
            "description_ar_style": "<p>اختر ما إذا كنت تريد أن يكون مقطعك عاديًا أو مطبوعًا أو لامعًا أو بلورات. ثم أضف اختيارك للاسم إلى التعليقات واختر ما إذا كنت تريد مقطعك على الوجهين/مع القلب.<br></p>\n",
            "main_image": "https://ksacdn4.mnasaticdn.com/uploads/product_image/3425/product_01725733862_thumb.jpg",
            "thumb_image": "https://ksacdn4.mnasaticdn.com/uploads/product_image/3425/product_01725733862_thumb.jpg",
            "min_variant_price": 0,
            "original_price": 1,
            "tax_percent": 0,
            "non_taxable": 0,
            "special_tag_en": "New",
            "special_tag_ar": "جديد",
            "quantity_discounts": []
        },
        {
            "product_id": "146",
            "title": "Puff Pastry",
            "title_ar": "Puff Pastry",
            "product_type": "1",
            "description": "Choose whether you would like your clip plain, printed, with glitter or crystals. Then add your choice of name to the comments and choose whether you would like your clip double sided/with heart.\r\n\n",
            "description_ar": "اختر ما إذا كنت تريد أن يكون مقطعك عاديًا أو مطبوعًا أو لامعًا أو بلورات. ثم أضف اختيارك للاسم إلى التعليقات واختر ما إذا كنت تريد مقطعك على الوجهين/مع القلب.\r\n\n",
            "sort_order": "0",
            "image": "uploads/product_image/3425/product_01725733951.jpg",
            "current_stock": "15",
            "sale_price": 1,
            "category": "2",
            "sub_category": "0",
            "digital_product": "0",
            "pdt_discount_type": 1,
            "preparation_time": "4320",
            "catering": "0",
            "branches": "ALL",
            "purchase_limit": "0",
            "pdt_tax_id": "0",
            "tag": "__tag_new",
            "track_inventory": "0",
            "discount": "0.00",
            "special_price_discount": "0",
            "cat_tax_id": "0",
            "preparation_time_text": {
                "en": "3 Days",
                "ar": "3 أيام"
            },
            "description_style": "<p>Choose whether you would like your clip plain, printed, with glitter or crystals. Then add your choice of name to the comments and choose whether you would like your clip double sided/with heart.<br></p>\n",
            "description_ar_style": "<p>اختر ما إذا كنت تريد أن يكون مقطعك عاديًا أو مطبوعًا أو لامعًا أو بلورات. ثم أضف اختيارك للاسم إلى التعليقات واختر ما إذا كنت تريد مقطعك على الوجهين/مع القلب.<br></p>\n",
            "main_image": "https://ksacdn4.mnasaticdn.com/uploads/product_image/3425/product_01725733951_thumb.jpg",
            "thumb_image": "https://ksacdn4.mnasaticdn.com/uploads/product_image/3425/product_01725733951_thumb.jpg",
            "min_variant_price": 0,
            "original_price": 1,
            "tax_percent": 0,
            "non_taxable": 0,
            "special_tag_en": "New",
            "special_tag_ar": "جديد",
            "quantity_discounts": []
        },
        {
            "product_id": "158",
            "title": "Crushed Ice clip",
            "title_ar": "Crushed Ice clip",
            "product_type": "1",
            "description": "\r\n\n",
            "description_ar": "\r\n\n",
            "sort_order": "0",
            "image": "uploads/product_image/3425/product_01733116937.jpeg",
            "current_stock": "23",
            "sale_price": 1,
            "category": "2",
            "sub_category": "0",
            "digital_product": "0",
            "pdt_discount_type": 1,
            "preparation_time": "0",
            "catering": "0",
            "branches": "ALL",
            "purchase_limit": "0",
            "pdt_tax_id": "0",
            "tag": "",
            "track_inventory": "0",
            "discount": "0.00",
            "special_price_discount": "0",
            "cat_tax_id": "0",
            "description_style": "<p><br></p>\n",
            "description_ar_style": "<p><br></p>\n",
            "main_image": "https://ksacdn4.mnasaticdn.com/uploads/product_image/3425/product_01733116937_thumb.jpeg",
            "thumb_image": "https://ksacdn4.mnasaticdn.com/uploads/product_image/3425/product_01733116937_thumb.jpeg",
            "min_variant_price": 0,
            "original_price": 1,
            "tax_percent": 0,
            "non_taxable": 0,
            "special_tag_en": "",
            "special_tag_ar": "",
            "quantity_discounts": []
        },
        {
            "product_id": "161",
            "title": "Sweetheart ",
            "title_ar": "Sweetheart ",
            "product_type": "1",
            "description": "\r\n\n",
            "description_ar": "\r\n\n",
            "sort_order": "0",
            "image": "uploads/product_image/3425/product_01733117432.jpeg",
            "current_stock": "12",
            "sale_price": 1,
            "category": "2",
            "sub_category": "0",
            "digital_product": "0",
            "pdt_discount_type": 1,
            "preparation_time": "0",
            "catering": "0",
            "branches": "ALL",
            "purchase_limit": "0",
            "pdt_tax_id": "0",
            "tag": "",
            "track_inventory": "0",
            "discount": "0.00",
            "special_price_discount": "0",
            "cat_tax_id": "0",
            "description_style": "<p><br></p>\n",
            "description_ar_style": "<p><br></p>\n",
            "main_image": "https://ksacdn4.mnasaticdn.com/uploads/product_image/3425/product_01733117432_thumb.jpeg",
            "thumb_image": "https://ksacdn4.mnasaticdn.com/uploads/product_image/3425/product_01733117432_thumb.jpeg",
            "min_variant_price": 0,
            "original_price": 1,
            "tax_percent": 0,
            "non_taxable": 0,
            "special_tag_en": "",
            "special_tag_ar": "",
            "quantity_discounts": []
        },
        {
            "product_id": "163",
            "title": "Deema x Saie",
            "title_ar": "Deema x Saie",
            "product_type": "1",
            "description": "A special collab between @Deemathedietitian &amp; @Saie.kw in a soft pink shade, perfect for everyday &amp; gym wear.\n",
            "description_ar": "A special collab between @Deemathedietitian &amp; @Saie.kw in a soft pink shade, perfect for everyday &amp; gym wear.\r\n\n",
            "sort_order": "0",
            "image": "uploads/product_image/3425/product_01736155405.jpg",
            "current_stock": "16",
            "sale_price": 1,
            "category": "2",
            "sub_category": "0",
            "digital_product": "0",
            "pdt_discount_type": 1,
            "preparation_time": "0",
            "catering": "0",
            "branches": "ALL",
            "purchase_limit": "0",
            "pdt_tax_id": "0",
            "tag": "__tag_limited",
            "track_inventory": "0",
            "discount": "0.00",
            "special_price_discount": "0",
            "cat_tax_id": "0",
            "description_style": "<p>A special collab between @Deemathedietitian &amp; @Saie.kw in a soft pink shade, perfect for everyday &amp; gym wear.</p>\n",
            "description_ar_style": "<p>A special collab between @Deemathedietitian &amp; @Saie.kw in a soft pink shade, perfect for everyday &amp; gym wear.<br></p>\n",
            "main_image": "https://ksacdn4.mnasaticdn.com/uploads/product_image/3425/product_01736155405_thumb.jpg",
            "thumb_image": "https://ksacdn4.mnasaticdn.com/uploads/product_image/3425/product_01736155405_thumb.jpg",
            "min_variant_price": 0,
            "original_price": 1,
            "tax_percent": 0,
            "non_taxable": 0,
            "special_tag_en": "Limited",
            "special_tag_ar": "محدود",
            "quantity_discounts": []
        },
        {
            "product_id": "168",
            "title": "Mini Clips",
            "title_ar": "Mini Clips",
            "product_type": "1",
            "description": "\r\n\r\n\r\n\n",
            "description_ar": "\r\n\r\n\r\n\n",
            "sort_order": "0",
            "image": "uploads/product_image/3425/product_01744826590.jpg",
            "current_stock": "3996",
            "sale_price": 0,
            "category": "2",
            "sub_category": "0",
            "digital_product": "0",
            "pdt_discount_type": 1,
            "preparation_time": "0",
            "catering": "0",
            "branches": "ALL",
            "purchase_limit": "0",
            "pdt_tax_id": "0",
            "tag": "",
            "track_inventory": "0",
            "discount": "0.00",
            "special_price_discount": "0",
            "cat_tax_id": "0",
            "description_style": "<p><br></p>\r\n\r\n\n",
            "description_ar_style": "<p><br></p>\r\n\r\n\n",
            "main_image": "https://ksacdn4.mnasaticdn.com/uploads/product_image/3425/product_01744826590_thumb.jpg",
            "thumb_image": "https://ksacdn4.mnasaticdn.com/uploads/product_image/3425/product_01744826590_thumb.jpg",
            "min_variant_price": 0,
            "original_price": 0,
            "tax_percent": 0,
            "non_taxable": 0,
            "special_tag_en": "",
            "special_tag_ar": "",
            "quantity_discounts": []
        },
        {
            "product_id": "174",
            "title": "Pocket Mirror",
            "title_ar": "Pocket Mirror",
            "product_type": "1",
            "description": "\r\n\n",
            "description_ar": "\r\n\n",
            "sort_order": "0",
            "image": "uploads/product_image/3425/product_01744827371.jpg",
            "current_stock": "97",
            "sale_price": 0,
            "category": "2",
            "sub_category": "0",
            "digital_product": "0",
            "pdt_discount_type": 1,
            "preparation_time": "0",
            "catering": "0",
            "branches": "ALL",
            "purchase_limit": "0",
            "pdt_tax_id": "0",
            "tag": "__tag_new",
            "track_inventory": "0",
            "discount": "0.00",
            "special_price_discount": "0",
            "cat_tax_id": "0",
            "description_style": "<p><br></p>\n",
            "description_ar_style": "<p><br></p>\n",
            "main_image": "https://ksacdn4.mnasaticdn.com/uploads/product_image/3425/product_01744827371_thumb.jpg",
            "thumb_image": "https://ksacdn4.mnasaticdn.com/uploads/product_image/3425/product_01744827371_thumb.jpg",
            "min_variant_price": 0,
            "original_price": 0,
            "tax_percent": 0,
            "non_taxable": 0,
            "special_tag_en": "New",
            "special_tag_ar": "جديد",
            "quantity_discounts": []
        },
        {
            "product_id": "106",
            "title": "DIY Custom Clip Set",
            "title_ar": "مجموع الشباصات",
            "product_type": "0",
            "description": "Make your own claw clip set: This is a perfect activity to do alone or with friends! The set comes with the following items: 6 Clips of your choice 6 Tweezers 3 Glue Packs 1 Box of multicoloured crystalsADD CLAW CLIP COLOUR CHOICES IN NOTE SECTION- (if not added we will add a random mix)\r\n\r\n\r\n\n",
            "description_ar": "اصنع مجموعة الشباصات الخاصة بك: هذا نشاط مثالي للقيام به بمفردك أو مع الأصدقاء! تأتي المجموعة مع العناصر التالية: \r\n 6 مقاطع من اختيارك 6 ملاقط 3 عبوات غراء 1 علبة كريستالات متعددة الألوان\r\n\r\n\r\n\n",
            "sort_order": "0",
            "image": "uploads/product_image/3425/product_01722279015.jpg",
            "current_stock": "7",
            "sale_price": 30,
            "category": "4",
            "sub_category": "0",
            "digital_product": "0",
            "pdt_discount_type": 1,
            "preparation_time": "1440",
            "catering": "0",
            "branches": "ALL",
            "purchase_limit": "0",
            "pdt_tax_id": "0",
            "tag": "__tag_new",
            "track_inventory": "0",
            "discount": "0.00",
            "special_price_discount": "0",
            "cat_tax_id": "0",
            "preparation_time_text": {
                "en": "1 Days",
                "ar": "1 يوم"
            },
            "description_style": "<p>Make your own claw clip set: This is a perfect activity to do alone or with friends! The set comes with the following items:</p><p></p><ul><li>6 Clips of your choice</li><li>6 Tweezers</li><li>3 Glue Packs</li><li>1 Box of multicoloured crystals</li></ul>ADD CLAW CLIP COLOUR CHOICES IN NOTE SECTION- (if not added we will add a random mix)\r\n\r\n\r\n\n",
            "description_ar_style": "<p>اصنع مجموعة الشباصات الخاصة بك: هذا نشاط مثالي للقيام به بمفردك أو مع الأصدقاء! تأتي المجموعة مع العناصر التالية:</p><p><br></p><p>6 مقاطع من اختيارك</p><p>6 ملاقط</p><p>3 عبوات غراء</p><p>1 علبة كريستالات متعددة الألوان</p>\r\n\r\n\r\n\n",
            "main_image": "https://ksacdn4.mnasaticdn.com/uploads/product_image/3425/product_01722279015_thumb.jpg",
            "thumb_image": "https://ksacdn4.mnasaticdn.com/uploads/product_image/3425/product_01722279015_thumb.jpg",
            "min_variant_price": 0,
            "original_price": 30,
            "tax_percent": 0,
            "non_taxable": 0,
            "special_tag_en": "New",
            "special_tag_ar": "جديد",
            "quantity_discounts": []
        },
        {
            "product_id": "149",
            "title": "Sugar Glaze Brush",
            "title_ar": "Sugar Glaze Brush",
            "product_type": "1",
            "description": "Add to WishlistThis pure bamboo brush is a plastic-free and high quality zero-waste alternative to your ordinary hair brush. Designed to glide through your hair smoothly, while teasing natural oils along each strand, this brush gives your hair a significantly shinier and healthier appearance and feel.Includes a ventilation hole to aid in drainage after the brush has been washed Organic bamboo handle &amp; bristles with biodegradable acetate back Due to hygienic reasons this item is finale sale. We are unable to accept any returns Slight variations in color may occur\r\n \r\n Choose whether you would like your brush plain, printed, with glitter or crystals. Then add your choice of name to the comments.\r\n\r\n\r\n\r\n\r\n\r\n\r\n\n",
            "description_ar": "Choose whether you would like your brush plain, printed, with glitter or crystals. Then add your choice of name to the comments.\r\n\r\n\r\n\r\n\r\n\r\n\r\n\n",
            "sort_order": "0",
            "image": "uploads/product_image/3425/product_01733117175.jpeg",
            "current_stock": "33",
            "sale_price": 3,
            "category": "7",
            "sub_category": "0",
            "digital_product": "0",
            "pdt_discount_type": 1,
            "preparation_time": "4320",
            "catering": "0",
            "branches": "ALL",
            "purchase_limit": "0",
            "pdt_tax_id": "0",
            "tag": "__tag_new",
            "track_inventory": "0",
            "discount": "0.00",
            "special_price_discount": "0",
            "cat_tax_id": "0",
            "preparation_time_text": {
                "en": "3 Days",
                "ar": "3 أيام"
            },
            "description_style": "<div id=\"shopify-block-wishlist_king_wishlist_button_block_KhdFAR\" class=\"shopify-block shopify-app-block\"><wishlist-button-block data-product-handle=\"bamboo-paddle-brush-in-pink-sugar\" align-self=\"left\" align-content=\"left\" full-width=\"\" show-icon=\"\" show-text=\"\" wk-loaded=\"\"><wk-button><button type=\"button\" aria-label=\"Add to Wishlist\" class=\"wk-button wk-align-left wk-align-content-left wk-full-width\"><span class=\"wk-text\">Add to Wishlist</span></button></wk-button></wishlist-button-block></div><div class=\"product-block\"><div class=\"rte\">This pure bamboo brush is a plastic-free and high quality zero-waste alternative to your ordinary hair brush. Designed to glide through your hair smoothly, while teasing natural oils along each strand, this brush gives your hair a significantly shinier and healthier appearance and feel.</div><div class=\"rte\"><ul><li>Includes a ventilation hole to aid in drainage after the brush has been washed</li><li>Organic bamboo handle &amp; bristles with biodegradable acetate back</li><li>Due to hygienic reasons this item is finale sale. We are unable to accept any returns</li><li>Slight variations in color may occur</li></ul></div></div><p><br></p><p><br></p><p>Choose whether you would like your brush plain, printed, with glitter or crystals. Then add your choice of name to the comments.<br></p>\r\n\r\n\r\n\r\n\r\n\r\n\n",
            "description_ar_style": "<p>Choose whether you would like your brush plain, printed, with glitter or crystals. Then add your choice of name to the comments.<br></p>\r\n\r\n\r\n\r\n\r\n\r\n\n",
            "main_image": "https://ksacdn4.mnasaticdn.com/uploads/product_image/3425/product_01733117175_thumb.jpeg",
            "thumb_image": "https://ksacdn4.mnasaticdn.com/uploads/product_image/3425/product_01733117175_thumb.jpeg",
            "min_variant_price": 0,
            "original_price": 3,
            "tax_percent": 0,
            "non_taxable": 0,
            "special_tag_en": "New",
            "special_tag_ar": "جديد",
            "quantity_discounts": []
        },
        {
            "product_id": "152",
            "title": "Leopard Brush",
            "title_ar": "Leopard Brush",
            "product_type": "1",
            "description": "Add to WishlistThis pure bamboo paddle brush is a plastic-free and high quality zero-waste alternative to your ordinary hair brush. Designed to glide through your hair smoothly, while teasing natural oils along each strand, this brush gives your hair a significantly shinier and healthier appearance and feel.Includes a ventilation hole to aid in drainage after the brush has been washed Organic bamboo handle &amp; bristles with biodegradable acetate Due to hygienic reasons this item is final sale. We are unable to accept any returns Slight variations in color may occur\r\n\r\n\r\n\r\n\n",
            "description_ar": "Choose whether you would like your brush plain, printed, with glitter or crystals. Then add your choice of name to the comments.\r\n\r\n\r\n\r\n\r\n\n",
            "sort_order": "0",
            "image": "uploads/product_image/3425/product_01733117261.jpeg",
            "current_stock": "36",
            "sale_price": 3,
            "category": "7",
            "sub_category": "0",
            "digital_product": "0",
            "pdt_discount_type": 1,
            "preparation_time": "4320",
            "catering": "0",
            "branches": "ALL",
            "purchase_limit": "0",
            "pdt_tax_id": "0",
            "tag": "__tag_new",
            "track_inventory": "0",
            "discount": "0.00",
            "special_price_discount": "0",
            "cat_tax_id": "0",
            "preparation_time_text": {
                "en": "3 Days",
                "ar": "3 أيام"
            },
            "description_style": "<div id=\"shopify-block-wishlist_king_wishlist_button_block_KhdFAR\" class=\"shopify-block shopify-app-block\"><wishlist-button-block data-product-handle=\"bamboo-paddle-brush-in-pink-sugar\" align-self=\"left\" align-content=\"left\" full-width=\"\" show-icon=\"\" show-text=\"\" wk-loaded=\"\"><wk-button><button type=\"button\" aria-label=\"Add to Wishlist\" class=\"wk-button wk-align-left wk-align-content-left wk-full-width\"><span class=\"wk-text\">Add to Wishlist</span></button></wk-button></wishlist-button-block></div><div class=\"product-block\"><div class=\"rte\">This pure <a href=\"https://www.emijay.com/collections/hairbrushes\" title=\"Bamboo Paddle Brush\">bamboo paddle brush</a> is a plastic-free and high quality zero-waste alternative to your ordinary hair brush. Designed to glide through your hair smoothly, while teasing natural oils along each strand, this brush gives your hair a significantly shinier and healthier appearance and feel.<ul><li>Includes a ventilation hole to aid in drainage after the brush has been washed</li><li>Organic bamboo handle &amp; bristles with biodegradable acetate</li><li>Due to hygienic reasons this item is <a title=\"return policy\" href=\"https://www.emijay.com/policies/refund-policy\" data-mce-fragment=\"1\" data-mce-href=\"/policies/refund-policy\">final sale</a>. We are unable to accept any returns</li><li>Slight variations in color may occur</li></ul></div></div>\r\n\r\n\r\n\r\n\n",
            "description_ar_style": "<p>Choose whether you would like your brush plain, printed, with glitter or crystals. Then add your choice of name to the comments.<br></p>\r\n\r\n\r\n\r\n\n",
            "main_image": "https://ksacdn4.mnasaticdn.com/uploads/product_image/3425/product_01733117261_thumb.jpeg",
            "thumb_image": "https://ksacdn4.mnasaticdn.com/uploads/product_image/3425/product_01733117261_thumb.jpeg",
            "min_variant_price": 0,
            "original_price": 3,
            "tax_percent": 0,
            "non_taxable": 0,
            "special_tag_en": "New",
            "special_tag_ar": "جديد",
            "quantity_discounts": []
        },
        {
            "product_id": "155",
            "title": "Crushed Ice Brush",
            "title_ar": "Crushed Ice Brush",
            "product_type": "1",
            "description": "\r\n\n",
            "description_ar": "\r\n\n",
            "sort_order": "0",
            "image": "uploads/product_image/3425/product_01733116167.jpeg",
            "current_stock": "32",
            "sale_price": 3,
            "category": "7",
            "sub_category": "0",
            "digital_product": "0",
            "pdt_discount_type": 1,
            "preparation_time": "0",
            "catering": "0",
            "branches": "ALL",
            "purchase_limit": "0",
            "pdt_tax_id": "0",
            "tag": "",
            "track_inventory": "0",
            "discount": "0.00",
            "special_price_discount": "0",
            "cat_tax_id": "0",
            "description_style": "<p><br></p>\n",
            "description_ar_style": "<p><br></p>\n",
            "main_image": "https://ksacdn4.mnasaticdn.com/uploads/product_image/3425/product_01733116167_thumb.jpeg",
            "thumb_image": "https://ksacdn4.mnasaticdn.com/uploads/product_image/3425/product_01733116167_thumb.jpeg",
            "min_variant_price": 0,
            "original_price": 3,
            "tax_percent": 0,
            "non_taxable": 0,
            "special_tag_en": "",
            "special_tag_ar": "",
            "quantity_discounts": []
        },
        {
            "product_id": "177",
            "title": "Makeup Bags",
            "title_ar": "Makeup Bags",
            "product_type": "0",
            "description": "The ultimate makeup pouches combining style and practicality in one\r\n\r\n\r\n\n\n\n\n\n",
            "description_ar": "\r\n\n\n\n\n\n",
            "sort_order": "0",
            "image": "uploads/product_image/3425/product_01747206365.jpg",
            "current_stock": "137",
            "sale_price": 5,
            "category": "11",
            "sub_category": "0",
            "digital_product": "0",
            "pdt_discount_type": 1,
            "preparation_time": "0",
            "catering": "0",
            "branches": "ALL",
            "purchase_limit": "0",
            "pdt_tax_id": "0",
            "tag": "",
            "track_inventory": "0",
            "discount": "0.00",
            "special_price_discount": "0",
            "cat_tax_id": "0",
            "description_style": "The ultimate makeup pouches combining style and practicality in one\r\n\r\n\r\n\n\n\n\n\n",
            "description_ar_style": "\r\n\n\n\n\n\n",
            "main_image": "https://ksacdn4.mnasaticdn.com/uploads/product_image/3425/product_01747206365_thumb.jpg",
            "thumb_image": "https://ksacdn4.mnasaticdn.com/uploads/product_image/3425/product_01747206365_thumb.jpg",
            "min_variant_price": 0,
            "original_price": 5,
            "tax_percent": 0,
            "non_taxable": 0,
            "special_tag_en": "",
            "special_tag_ar": "",
            "quantity_discounts": []
        },
        {
            "product_id": "113",
            "title": "Starfish Clip",
            "title_ar": "Starfish Clip",
            "product_type": "0",
            "description": "\r\n\n",
            "description_ar": "\r\n\n",
            "sort_order": "0",
            "image": "uploads/product_image/3425/product_01723224829.jpeg",
            "current_stock": "1",
            "sale_price": 3,
            "category": "14",
            "sub_category": "0",
            "digital_product": "0",
            "pdt_discount_type": 1,
            "preparation_time": "0",
            "catering": "0",
            "branches": "ALL",
            "purchase_limit": "0",
            "pdt_tax_id": "0",
            "tag": "",
            "track_inventory": "0",
            "discount": "0.00",
            "special_price_discount": "0",
            "cat_tax_id": "0",
            "description_style": "<p><br></p>\n",
            "description_ar_style": "<p><br></p>\n",
            "main_image": "https://ksacdn4.mnasaticdn.com/uploads/product_image/3425/product_01723224829_thumb.jpeg",
            "thumb_image": "https://ksacdn4.mnasaticdn.com/uploads/product_image/3425/product_01723224829_thumb.jpeg",
            "min_variant_price": 0,
            "original_price": 3,
            "tax_percent": 0,
            "non_taxable": 0,
            "special_tag_en": "",
            "special_tag_ar": "",
            "quantity_discounts": []
        },
        {
            "product_id": "116",
            "title": "Starfish XL Clip",
            "title_ar": "Starfish XL Clip",
            "product_type": "0",
            "description": "\r\n\n",
            "description_ar": "\r\n\n",
            "sort_order": "0",
            "image": "uploads/product_image/3425/product_01723224964.jpeg",
            "current_stock": "0",
            "sale_price": 3,
            "category": "14",
            "sub_category": "0",
            "digital_product": "0",
            "pdt_discount_type": 1,
            "preparation_time": "0",
            "catering": "0",
            "branches": "ALL",
            "purchase_limit": "0",
            "pdt_tax_id": "0",
            "tag": "",
            "track_inventory": "0",
            "discount": "0.00",
            "special_price_discount": "0",
            "cat_tax_id": "0",
            "description_style": "<p><br></p>\n",
            "description_ar_style": "<p><br></p>\n",
            "main_image": "https://ksacdn4.mnasaticdn.com/uploads/product_image/3425/product_01723224964_thumb.jpeg",
            "thumb_image": "https://ksacdn4.mnasaticdn.com/uploads/product_image/3425/product_01723224964_thumb.jpeg",
            "min_variant_price": 0,
            "original_price": 3,
            "tax_percent": 0,
            "non_taxable": 0,
            "special_tag_en": "",
            "special_tag_ar": "",
            "quantity_discounts": []
        },
        {
            "product_id": "119",
            "title": "Ocean Clip",
            "title_ar": "Ocean Clip",
            "product_type": "0",
            "description": "\r\n\r\n\n",
            "description_ar": "\r\n\r\n\n",
            "sort_order": "0",
            "image": "uploads/product_image/3425/product_01723225107.jpeg",
            "current_stock": "0",
            "sale_price": 4,
            "category": "14",
            "sub_category": "0",
            "digital_product": "0",
            "pdt_discount_type": 1,
            "preparation_time": "0",
            "catering": "0",
            "branches": "ALL",
            "purchase_limit": "0",
            "pdt_tax_id": "0",
            "tag": "",
            "track_inventory": "0",
            "discount": "0.00",
            "special_price_discount": "0",
            "cat_tax_id": "0",
            "description_style": "<p><br></p>\r\n\n",
            "description_ar_style": "<p><br></p>\r\n\n",
            "main_image": "https://ksacdn4.mnasaticdn.com/uploads/product_image/3425/product_01723225107_thumb.jpeg",
            "thumb_image": "https://ksacdn4.mnasaticdn.com/uploads/product_image/3425/product_01723225107_thumb.jpeg",
            "min_variant_price": 0,
            "original_price": 4,
            "tax_percent": 0,
            "non_taxable": 0,
            "special_tag_en": "",
            "special_tag_ar": "",
            "quantity_discounts": []
        }
    ]
}